IProgress/Progress.py
IProgress/__init__.py
IProgress_DarkSourceOfCode-0.0.1.dist-info/LICENSE
IProgress_DarkSourceOfCode-0.0.1.dist-info/METADATA
IProgress_DarkSourceOfCode-0.0.1.dist-info/WHEEL
IProgress_DarkSourceOfCode-0.0.1.dist-info/top_level.txt
IProgress_DarkSourceOfCode-0.0.1.dist-info/RECORD
