Metadata-Version: 2.1
Name: IProgress-DarkSourceOfCode
Version: 0.0.1
Summary: Iprogress is an IPython shell progress checker
Home-page: https://github.com/jayanta-banik/IProgress
Author: Jayanta Banik
Author-email: sciencenerd1609@gmail.com
License: UNKNOWN
Platform: UNKNOWN
Classifier: Programming Language :: Python :: 3
Classifier: License :: OSI Approved :: MIT License
Classifier: Operating System :: OS Independent
Requires-Python: >=3.5
